toolnvt/ToolNVT.py
toolnvt/__init__.py
toolnvt-1.0.0.dist-info/LICENSE.txt
toolnvt-1.0.0.dist-info/METADATA
toolnvt-1.0.0.dist-info/WHEEL
toolnvt-1.0.0.dist-info/entry_points.txt
toolnvt-1.0.0.dist-info/top_level.txt
toolnvt-1.0.0.dist-info/RECORD
